MANIFEST.in
README.rst
canvas_api.py
setup.cfg
setup.py
py_canvas_api/__init__.py
py_canvas_api/canvas_api.py
py_canvas_api/canvas_data.py
py_canvas_api/catalog.py
py_canvas_api/common.py
py_canvas_api/commons.py
py_canvas_api/rester_api.py
py_canvas_api/sis_importer.py
py_canvas_api.egg-info/PKG-INFO
py_canvas_api.egg-info/SOURCES.txt
py_canvas_api.egg-info/dependency_links.txt
py_canvas_api.egg-info/requires.txt
py_canvas_api.egg-info/top_level.txt