Metadata-Version: 1.0
Name: py-canvas-api
Version: 0.2.2
Summary: A very small library for accessing the API for the Canvas LMS.
Home-page: https://github.com/kajigga/py_canvas_api
Author: UNKNOWN
Author-email: UNKNOWN
License: UNKNOWN
Keywords: canvaslms,api
Platform: UNKNOWN
